fga/__init__.py
fga/client.py
fga/config.py
fga/constants.py
fga/entity.py
fga/event.py
fga/exception.py
fga/http_client.py
fga/plugin.py
fga/processor.py
fga/storage.py
fga/timeline.py
fga/utils.py
fga/worker.py
footprint_analytics-0.1.9.dist-info/LICENSE
footprint_analytics-0.1.9.dist-info/METADATA
footprint_analytics-0.1.9.dist-info/WHEEL
footprint_analytics-0.1.9.dist-info/top_level.txt
footprint_analytics-0.1.9.dist-info/RECORD
