Metadata-Version: 2.1
Name: footprint-analytics
Version: 0.1.9
Summary: The official FGA backend Python SDK for server-side instrumentation.
Home-page: UNKNOWN
Author: rowland
Author-email: rowland@footprint.network
License: MIT License
Keywords: fga,python,backend
Platform: UNKNOWN
Classifier: Development Status :: 5 - Production/Stable
Classifier: Intended Audience :: Developers
Classifier: License :: OSI Approved :: MIT License
Classifier: Programming Language :: Python :: 3
Classifier: Programming Language :: Python :: 3.6
Classifier: Programming Language :: Python :: 3.7
Classifier: Programming Language :: Python :: 3.8
Classifier: Programming Language :: Python :: 3.9
Classifier: Programming Language :: Python :: 3.10
Requires-Python: >=3.6, <4
Requires-Dist: pydash
Requires-Dist: requests
